cmbscat/__init__.py
cmbscat/cmbscat_class.py
cmbscat-0.0.2.dist-info/LICENSE
cmbscat-0.0.2.dist-info/METADATA
cmbscat-0.0.2.dist-info/WHEEL
cmbscat-0.0.2.dist-info/top_level.txt
cmbscat-0.0.2.dist-info/RECORD
