Metadata-Version: 2.2
Name: cmbscat
Version: 0.0.2
Summary: A package for scattering covariance synthesis on datasets of Healpix maps, based on the HealpixML package.
Author-email: Paolo CAMPETI <paolo.campeti@fe.infn.it>, Jean-Marc DELOUIS <jean.marc.delouis@ifremer.fr>
License: BSD 3-Clause License
Keywords: scattering covariance,scattering transform,healpy,gradient descent,microcanonical,wavelet,HealpixML,Healpix,generative models
Classifier: Programming Language :: Python :: 3
Classifier: License :: OSI Approved :: MIT License
Classifier: Operating System :: OS Independent
Requires-Python: >=3.9
License-File: LICENSE
Requires-Dist: numpy
Requires-Dist: matplotlib
Requires-Dist: healpy
Requires-Dist: tensorflow
Requires-Dist: healpixml
Requires-Dist: tqdm
